[
  {
    "chunk_idx": 0,
    "page_name": "工具行业-广告审核规则解读",
    "title": "1.常见违规问题​",
    "page_url": "总知识库_cleaned/巨量广告规则中心/行业规范及案例指引/行业规范/工具行业-广告审核规则解读.html",
    "summary": "电商平台广告需遵守《广告法》，包括人物授权、真实性、禁用虚假内容、禁止低俗迷信等，违规将受处罚。规则详情可在巨量广告平台查看。",
    "question": "在巨量广告平台上，发布广告时如何确保不违反人物授权、虚假诱导、虚假误导等广告审核规则？",
    "text": "1.常见违规问题1.1缺少人物授权📌《广告法》第三章  第三十三条广告主或者广告经营者在广告中使用他人名义或者形象的，应当事先取得其书面同意；使用无民事行为能力人、限制民事行为能力人的名义或者形象的，应事先取得其监护人书面同意关于授权相关的广告审核要求：人物授权：广告内容涉及明星、名人、大师等人物的名义、肖像等内容，需提供相应授权；版权授权：广告内容涉及第三方影视/动漫/文学作品等，需提供版权授权。违规理由规则解读广告素材案例解读1.2涉及诱导用户点击的内容📌《广告法》第一章  第四条广告不得含有虚假或者引人误解的内容，不得欺骗、误导消费者。广告主应当对广告内容的真实性负责。《广告法》第二章  第二十八条广告以虚假或者引人误解的内容误导消费者的，构成虚假广告。广告素材中不得涉及误导用户的：虚假系统提示、浮窗、弹窗类等内容。违规理由规则解读广告素材案例解读1.3涉及虚假误导内容📌《广告法》第一章  第四条广告不得含有虚假或者引人误解的内容，不得欺骗、误导消费者。广告主应当对广告内容的真实性负责。《广告法》第二章  第二十八条广告以虚假或者引人误解的内容误导消费者的，构成虚假广告。违规理由规则解读广告素材案例解读1.4任务赚钱：实物奖励或金额奖励虚假📌《广告法》第一章  第四条广告不得含有虚假或者引人误解的内容，不得欺骗、误导消费者。广告主应当对广告内容的真实性负责。《广告法》第二章  第二十八条广告以虚假或者引人误解的内容误导消费者的，构成虚假广告。违规理由规则解读广告素材案例解读1.5我司产品名义及产品logo📌未经许可不得以任何形式直接或间接地使用今日头条、抖音或其关联公司的商标、商号，如不得模仿抖音产品商标字样、抖音logo；未经许可不得以今日头条、抖音及关联公司或该等公司之工作人人员的名义作为广告宣传的手段。违规理由规则解读广告素材案例解读1.6中危禁投📌广告中不得涉及暂不接受投放的中危行业或内容等。违规理由规则解读广告素材案例解读1.7两性低俗📌《广告法》第二章  第九条广告不得有下列情形：（八）含有淫秽、色情、赌博、迷信、恐怖、暴力的内容；违规理由规则解读广告素材案例解读1.8涉及封建迷信📌《广告法》第二章  第九条广告不得有下列情形：（八）含有淫秽、色情、赌博、迷信、恐怖、暴力的内容；违规理由规则解读广告素材案例解读2.其他规则在哪里看2.1禁投相关规则关于投放相关规则在巨量广告平台均可查看•禁投规则•行业审核规则•规则变更•治理公告•......50%50%2.2规则中心知识图谱登录入口https://business.oceanengine.com/brand/index>>新手引导投放平台入驻开户•推广投放操作•本地推可推类目明细•入驻流程（电脑端）•准入&管控规则指引•开户指引•禁止推广品类资质提交•资质审核规范•结合投放类目提交资质•广告审核资质规则解读•开户资质要求•资质高频拒绝理由解读计划投放•广告审核管控规范•行业审核规范•广告推广页面-使用手册•千川广告审核规则•广告计划通用审核规范•行业审核规范•广告审核管控规范•千川创作避坑指南•广告新规速递通知下线/判罚•本地推治理规则•千川广告治理规则•广告判罚规则",
    "time": "2025-02-11 15:46:05"
  }
]