[
  {
    "chunk_idx": 0,
    "page_name": "行业准入规范调整_禁止宣传黄金回收",
    "title": "一、调整规范​",
    "page_url": "总知识库_cleaned/巨量广告规则中心/规则变更及信息公示/规则速递/行业准入规范调整_禁止宣传黄金回收.html",
    "summary": "针对黄金回收业务宣传误导消费者问题，调整规范禁止广告宣传黄金回收等业务，并扩大执行范围至AD本地服务和非电商直播平台。",
    "question": "平台对于黄金回收相关业务的广告宣传有何具体规定？",
    "text": "背景：近期经治理发现，黄金回收业务通过“高价回收”字样获客，但实际交易时单价、纯度、克重等检测结果不符合消费者预期。且在部分熔化称重环节，因为黄金饰品原形态无法恢复，导致消费者对最终价格有争议时无法申诉，易带来较高的投诉与体验问题。因此，作出如下规范调整。一、调整规范广告内容中，禁止宣传黄金回收、黄金变现、闲置黄金流通、黄金估价、黄金换新、黄金鉴定此类业务•常见的违规案例：◦黄金10秒在线估价,免费上门回收,快速变现！◦黄金回收价格高！不收任何手续费，一小时内免费上门回收◦黄金回收价格暴跌？不要担心，黄金回收595元一克，同城上门回收！33%33%33%二、执行范围AD本地服务、非电商直播（包含ad、本地推、千川非挂车、dou+、企业号、星图）",
    "time": "2024-05-06 16:25:12"
  }
]