[
  {
    "chunk_idx": 0,
    "page_name": "广告素材规范调整_禁止代写论文_公文_各类评定材料",
    "title": "一、调整规范​",
    "page_url": "总知识库_cleaned/巨量广告规则中心/规则变更及信息公示/规则速递/广告素材规范调整_禁止代写论文_公文_各类评定材料.html",
    "summary": "背景：经近期治理发现，代写类广告集中出现代写论文、公文等内容，AI代写尤其突出，暗示鼓励抄袭、作弊等不利于社会导向的行为，易引发学术、评审不诚信的问题。经评估，现作出如下调整。一、调整规范广告不得涉及代写学术、评定、各类考试/报名/竞赛的申报材料等内容（包括AI代写）不得涉及代写论文、作业、学术汇报",
    "question": "平台对于广告中涉及代写论文、公文等内容的操作有何规定，违规会有怎样的处理？",
    "text": "背景：经近期治理发现，代写类广告集中出现代写论文、公文等内容，AI代写尤其突出，暗示鼓励抄袭、作弊等不利于社会导向的行为，易引发学术、评审不诚信的问题。经评估，现作出如下调整。一、调整规范广告不得涉及代写学术、评定、各类考试/报名/竞赛的申报材料等内容（包括AI代写）不得涉及代写论文、作业、学术汇报材料不得涉及代写公务文书、评定评级、涉政类材料不得涉及代写各类考试考试/报名/竞赛所需的申报材料违规案例",
    "time": "2023-11-20 17:11:07"
  }
]