[
  {
    "chunk_idx": 0,
    "page_name": "_即时零售__发布不当信息_不友善内容_实施细则",
    "title": "一、什么是“不友善内容”？​",
    "page_url": "总知识库_cleaned/抖音电商规则中心/即时零售/创作者管理/_即时零售__发布不当信息_不友善内容_实施细则.html",
    "summary": "抖音电商禁止发布侮辱、威胁、骚扰等不友善内容，违规将根据情节严重程度进行警告、下架商品、冻结销售额、关闭分享权限等处罚。",
    "question": "抖音平台对于发布不友善内容的违规行为有哪些具体的处理措施？",
    "text": "一、什么是“不友善内容”？指创作者在直播/短视频进行商品分享及服务处理（包括但不限于飞鸽、评论等）过程中，出现以下场景：侮辱、谩骂、诅咒、污蔑、歧视或攻击他人的语言或行为；威胁：让他人产生恐慌、不安全等感受的任何内容、语言或者行为，威胁的内容包括但不限于他人的隐私、名誉、住址、财产及人身安全；频繁发送消息造成打扰：达人通过包括但不限于短信、邮件、飞鸽等方式向他人频繁、大量发送消息，对他人造成骚扰等。二、有哪些行为会被判定为“不友善内容”？此违规行为通常出现在口播、字幕、直播/短视频画面、管理员评论、回复消费者等场景，创作者口播/展示/回复不友善内容，包括但不限于以下行为：针对某个对象或群体进行侮辱、谩骂、诅咒、污蔑、歧视、人身攻击等不友善行为；对镜头做出侵犯性或攻击性动作，比如“抡巴掌”“出拳”“抹脖子”“竖中指”等。三、出现“不友善内容”的违规行为平台会如何处理？违规情节情节描述违规处理情节轻微1-2次违规，未造成负面影响的非故意违规。警告、下架违规商品。情节一般单场直播中违规次数3次；短视频14 天内违规次数3～6次；或造成消费者或商家体验实质损害，但影响较轻，未产生恶劣影响。下架单个商品，在佣金账户中冻结违规商品销售额所有订单成交额5%周期30天。情节严重单场直播中违规次数达3次以上；短视频14 天内违规次数6次以上；或对消费者、商家造成人身安全、财产损失的损害，利用多个关联账号恶意规避平台处罚。下架违规商品，在佣金账户中冻结带货违规商品或直播间整场订单成交金额（5%-10%）周期30天，关闭商品分享权限1天（为在创作者承担违规后果的同时正常运营不被阻断，平台提供缴纳200元违约金的处置方式供创作者自行选择。违约金的适用场景详见《抖音电商创作者违约金管理规范》）。情节特别严重对消费者、商家造成严重不良影响，引发极大量消费者/商家投诉的违规；对平台造成或可能造成严重负面影响的违规；利用多个关联账号违规，违规情节恶劣，恶意规避平台处罚。下架全部商品、永久关闭商品分享权限，视恶意程度冻结佣金账户30天或180天。全屏展示退出",
    "time": "2024-10-08 23:16:02"
  }
]