[
  {
    "chunk_idx": 0,
    "page_name": "什么是巨量创意",
    "title": "什么是巨量创意",
    "page_url": "总知识库_cleaned/巨量千川帮助中心/平台信息/基础信息介绍/什么是巨量创意.html",
    "summary": "什么是巨量创意巨量引擎旗下的营销创意交流服务平台。通过剖析大量优秀广告创意，帮助广告从业者快速提升创意广告制作技巧，打通广告主和创作者两端，解决创意生产流程中的三大痛点，实现创意广告的高效产出。可下载巨量创意APP进行使用：•搜索下载：各大应用商店搜索“巨量创意”即可；•二维码下载：扫描下方二维码即可完成下载；",
    "text": "什么是巨量创意巨量引擎旗下的营销创意交流服务平台。通过剖析大量优秀广告创意，帮助广告从业者快速提升创意广告制作技巧，打通广告主和创作者两端，解决创意生产流程中的三大痛点，实现创意广告的高效产出。可下载巨量创意APP进行使用：•搜索下载：各大应用商店搜索“巨量创意”即可；•二维码下载：扫描下方二维码即可完成下载；",
    "time": "2023-04-14 19:42:32"
  }
]