[
  {
    "chunk_idx": 0,
    "page_name": "_酒类赠品_组套类_商品发布细则",
    "title": "一、适用范围​",
    "page_url": "总知识库_cleaned/抖音电商规则中心/行业市场/行业商品管理/行业商品发布细则/_酒类赠品_组套类_商品发布细则.html",
    "summary": "本细则规范酒类赠品及组套商品发布，要求商家资质合规，遵循定准类目规则，正确分类商品，并在标题、主图、商详页明确标注“组套”信息。",
    "question": "在抖音电商平台上，发布含有酒类赠品或组套商品的商家，需要遵守哪些发布要求和资质规定，如果违规发布会有怎样的处理措施？",
    "text": "一、适用范围本规范适用于经营商品中含有酒类赠品或酒类组套商品的场景。赠品：指消费者以购买交易商品为前提而获得的商家承诺或双方约定的赠予物品或服务。商家开展合法有奖销售的，消费者中奖所获的奖品亦视为赠品。组套商品：2个及以上同类目或跨类目商品组合成的套装商品，酒类组套商品举例如下：举例1：白酒+葡萄酒举例2：酒+酒杯套组商家发布酒类赠品需遵守《赠品管理规范》，此外，组套商品和赠品需同时遵守以下要求：二、酒类赠品/组套商品资质要求1.商家售卖的组套商品及随商品附赠的赠品需为营业执照经营范围内包含的商品。2.组套商品内酒类商品需有完整链路二级及以上品牌授权。3.如商家未按照上述资质要求发布了组套商品或赠品，将按照《【商家—未按规则提交资质材料】细则》对商家进行处理。三、酒类赠品/组套商品发布要求1.定准要求（1）酒为定向准入类目，任何非酒类目准入商家不得以任何形式售卖含有酒的商品。（形式包括但不限于赠品、以酒杯为销售主体的套盒、礼盒等）（2）如赠品或组套商品包含定准商品，商家及品牌需为该类目定准商家、品牌，需遵循定准类目规则，所有定准类目详见《商家定向准入细则》。（3）如商家未按照上述定准要求发布了特定定准类目、品牌的礼盒或赠品，将按照《【商家—发布非约定商品】细则》对商家进行处理。举例：国产葡萄酒（品牌：张裕）+ 人头马进口洋酒 >>> 需放在国产葡萄酒类目下。2.类目要求（1）随商品附赠的赠品需放在相对应的商品类目中，如：酒杯：餐饮具 > 酒壶/酒杯/酒具 > 酒杯醒酒器：餐饮具 > 酒壶/酒杯/酒具 > 醒酒器开瓶器：餐饮具 > 酒壶/酒杯/酒具 > 开瓶器（2）如组套商品中包含国产葡萄酒、国产洋酒、国产威士忌商品，则组套商品需发布在如上三个类目中。（3）如组套商品中不包含国产葡萄酒、国产洋酒、国产威士忌商品，则组套商品需发布在更贴近礼盒主体的酒类目下。（4）如商家不按照如上要求进行类目乱挂，将按照《【商家—滥发信息】细则》——错放类目对商家进行处理。3.标题要求若商家售卖的酒类商品为组套商品，需在商品标题标明“组套”或“套装”信息。4.主图要求若商家售卖的酒类商品为组套商品，需展示内容物图片、标签图片。5.商详页要求若商家售卖的酒类商品为组套商品，需在商详页标明“组套”或“套装”信息，并展示套装内商品内容（包括品牌、商品名称、规格、数量等），不允许仅发套装外观不明确商品类型。附：了解如何创建组套商品，请点击【境内】组合商品创建指南。",
    "time": "2023-08-30 11:22:11"
  }
]