[
  {
    "chunk_idx": 0,
    "page_name": "_广告审核规范_不得使用难以核实_无法核实的人设做推荐证明",
    "title": "【广告审核规范】不得使用难以核实/无法核实的人设做推荐证明",
    "page_url": "总知识库_cleaned/巨量千川规则中心/规则变更及信息公示/规则速递/_广告审核规范_不得使用难以核实_无法核实的人设做推荐证明.html",
    "summary": "该文档主要针对平台广告审核规范进行解读，强调广告中不得使用难以核实或无法核实的人设做推荐证明，不得自称或描述存在虚假身份的人设，防止虚假人设误导消费者，违反广告法规定。同时，通过案例讲解，提醒广告主需对广告内容的真实性负责，避免法律风险。",
    "text": "【广告审核规范】不得使用难以核实/无法核实的人设做推荐证明【背景】近期，平台在治理中发现，部分广告使用虚假人设为产品/服务做推广，易对消费者造成误导。现针对该类素材的管控做进一步明确。【规则解读】•规则准则：广告内容中不得使用难以核实/无法核实的人设做推荐证明，不得自称、或描述存在xx身份/姓名/职位的虚假人设，为产品/服务做背书。•解读：在无事实依据的情况下，通过强调自身或他人身份/姓名/职位等，提升用户信任感，从而明示、暗示、演绎产品值得信赖、效果明显等，存在虚构人设风险。该场景中人设虚假，违反广告法中“广告不得含有虚假或者引人误解的内容，不得欺骗、误导消费者。广告主应当对广告内容的真实性负责”的要求，存在较高法律风险。•案例讲解违规案例违规点解读50%50%素材为两个连续画面。素材中表述“让我们听听中国企业家董事长怎么说”，随后画面跳转至“专家”进行产品功效讲解，并在图片中出现“钟老”的身份。素材中的「中国企业家董事长」、「钟老」存在虚构人设的情况，通过树立专业形象提高产品可信度，需管控。素材中以“广东石先生”的采访音频为背书，希望通过第三方人来证明产品效果，存在虚构第三方证明人设的情形，需管控。",
    "time": "2025-03-03 18:03:15"
  }
]