[
  {
    "chunk_idx": 0,
    "page_name": "抖店app全域推广投放指南",
    "title": "一、商品全域推广投放指南​ 表格行1-3",
    "page_url": "总知识库_cleaned/巨量千川帮助中心/产品功能相关/移动端相关/抖店app-千川/抖店app全域推广投放指南.html",
    "summary": "抖店app全域推广投放指南强调优先选择店铺主推品，支持多品建计划，参与千川活动商品可获红包补贴；建议参考系统建议出价，灵活调整ROI目标，避免频繁调整计划，并推荐使用智能优惠券和长期投放。",
    "question": "如何在抖店app中使用全域推广功能，设置合适的出价和调整策略以快速起量？",
    "text": "• 优先选择「店铺主推品」即跑量优选商品投放，能快速度过冷启 （算法结合商家历史投放数据和大盘趋势筛选的预估跑量能力较好的商品）；  • 商品全域推广支持多品一起建计划 ，勾选多品即可，系统会根据多个商品的数据综合给出ROI建议  • 若商品可参与千川活动， 会带上【红包补贴】标识 ，投放此类商品有机会获得平台消返红包 \n• 优先参考系统的建议出价，前期建议全域ROI可尝试降低5%-10%设置，先以快速起量为目标：  ◦ 如一直未起量，ROI目标可适当再调低些，每次调整幅度建议不要超过20%（即当前出价为4，调低不要低于3.2）；如果目前计划跑量快，且ROI较低，可适当提升商品全域ROI目标，每次调整幅度不要超过5%，即当天ROI为4，调高不要高于4.2；  ◦ 尽量避免对计划频繁的调整，如需调整，时间间隔大于1小时（以免影响当日的成本保障） \n• 建议默认使用智能优惠券（即勾选可选权益，平台为你发券引流）、默认长期投放、日预算充足； ",
    "time": "2024-12-30 11:43:41"
  }
]