[
  {
    "chunk_idx": 0,
    "page_name": "宠物驱虫_活体类限制推广商品创作者准入细则",
    "title": "​经营大类​​​一级类目名称​​​二级类目​​​三级类目​​​四级类目​​​推广资格说明​​​联",
    "page_url": "总知识库_cleaned/抖音电商规则中心/精选联盟/作者添加商品/实施细则/宠物驱虫_活体类限制推广商品创作者准入细则.html",
    "summary": "该文档主要规定了宠物药品及药剂类目的推广资格和商家型创作者的准入要求。联盟型创作者需通过精选联盟带货创作者，具备一定等级和无违规记录等条件。商家型创作者需与有类目经营权限的商家绑定，满足一系列规则，如保证店铺保证金足额缴纳和近期有对应类目订单成交等。同时，文档还规定了准出标准和禁入场景，如商家型创作者绑定的店铺无类目经营权限或经营异常，以及宠物活体水族类目的创作者禁止推广爬行类活体昆虫等。整份文档强调了推广资格和规则要求，旨在保障消费者权益和平台秩序。",
    "text": "经营大类一级类目名称二级类目三级类目四级类目推广资格说明联盟型创作者准入要求商家型创作者准入要求亲子生活宠物/宠物食品及用品动物药品及药剂宠物驱虫/创作者可推广动物药品及药剂类目的商品1.联盟型创作者：通过精选联盟带货创作者（含混合经营模式创作者）2.准入要求：（1）创作者等级≥L3级（2）近30天内无以下场景的违规处罚记录：推广禁售商品、推广假冒商品、侵权、诱导第三方、欺诈、不当获利等（3）近60天内因虚假宣传被关闭商品分享权限的次数<2次（4）近30天内虚假宣传违规次数<=3次（5）通过类目创作者考试3.准出标准：作者不再符合准入要求1.商家型创作者：店铺绑定人店一体账号、店铺授权号2.准入要求：（1）仅限与有类目经营权限的商家绑定的商家型创作者申请商家有类目经营权限，具体指店铺需前置满足以下全部规则：①店铺对应定准类目经营保证金足额缴纳②店铺近期有对应定准类目订单成交（2）通过类目创作者考试3.准出标准：（1）商家型创作者绑定的店铺无类目经营权限（保证金缴纳不足等）（2）商家型创作者绑定的店铺经营异常（即店铺被清退/停业，或出现其他严重违规行为）宠物活体水族活体鱼创作者可推广宠物活体类目的商品龟/鳖蟹虾螺蛙猫咪活体/鸟禽类活体/鼠类活体/爬行类活体蚕宝宝活体狗狗活体/仓鼠活体/兔子活体/鹦鹉活体/爬行类活体螳螂爬行类活体甲虫爬行类活体蟋蟀活体爬行类活体蝎类活体爬行类活体蜘蛛活体爬行类活体蚂蚁活体特种养殖（水族类）观赏海洋生物守宫蜥蜴活体/全屏展示退出",
    "time": "2025-05-14 12:16:28"
  }
]